pydecomposer/__init__.py
pydecomposer/pydecomposer.py
pydecomposer-1.1.5.dist-info/LICENSE
pydecomposer-1.1.5.dist-info/METADATA
pydecomposer-1.1.5.dist-info/WHEEL
pydecomposer-1.1.5.dist-info/top_level.txt
pydecomposer-1.1.5.dist-info/RECORD
