Metadata-Version: 2.1
Name: pydecomposer
Version: 1.1.5
Summary: A tool for advanced signal decomposition using VMD and CEEMDAN
Home-page: https://github.com/gems-yc4923/PyDecomposer
Author: Yassine Charouif
Author-email: yc4923@ic.ac.uk
Keywords: signal decomposition vmd ceemdan
Classifier: Development Status :: 4 - Beta
Classifier: Intended Audience :: Developers
Classifier: Intended Audience :: Science/Research
Classifier: License :: OSI Approved :: Apache Software License
Classifier: Programming Language :: Python :: 3
Classifier: Programming Language :: Python :: 3.7
Classifier: Programming Language :: Python :: 3.8
Classifier: Programming Language :: Python :: 3.9
Requires-Python: >=3.7
License-File: LICENSE
Requires-Dist: numpy
Requires-Dist: vmdpy
Requires-Dist: EntropyHub
Requires-Dist: PyEMD
Requires-Dist: matplotlib
